ndicom_gauss_kernel_kmeans/__init__.py
ndicom_gauss_kernel_kmeans/plugin.py
ndicom_gauss_kernel_kmeans/extension/build/Darwin/libgauss_kernel_kmeans.dylib
ndicom_gauss_kernel_kmeans-0.0.1.dev0.dist-info/METADATA
ndicom_gauss_kernel_kmeans-0.0.1.dev0.dist-info/RECORD
ndicom_gauss_kernel_kmeans-0.0.1.dev0.dist-info/WHEEL
ndicom_gauss_kernel_kmeans-0.0.1.dev0.dist-info/dependency_links.txt
ndicom_gauss_kernel_kmeans-0.0.1.dev0.dist-info/top_level.txt
